transformplot3d/__init__.py
transformplot3d/core/__init__.py
transformplot3d/core/quiver.py
transformplot3d/core/vectors.py
transformplot3d-0.0.4.dist-info/LICENSE
transformplot3d-0.0.4.dist-info/METADATA
transformplot3d-0.0.4.dist-info/WHEEL
transformplot3d-0.0.4.dist-info/top_level.txt
transformplot3d-0.0.4.dist-info/RECORD
