Metadata-Version: 2.2
Name: transformplot3d
Version: 0.0.4
Summary: Helper for plotting 3d vectors and coordinate systems.
Author: jan Sani
Author-email: <santipt50@gmail.com>
Keywords: python,matrix,matrix transformation,transformations,plot,3d plot,quiver
Classifier: Development Status :: 3 - Alpha
Classifier: Intended Audience :: Education
Classifier: Framework :: Matplotlib
Classifier: Programming Language :: Python :: 3
Classifier: Programming Language :: Python :: 3.12
Classifier: Operating System :: Microsoft :: Windows
License-File: LICENSE
Requires-Dist: transformations
Requires-Dist: numpy
Dynamic: author
Dynamic: author-email
Dynamic: classifier
Dynamic: description
Dynamic: description-content-type
Dynamic: keywords
Dynamic: requires-dist
Dynamic: summary
